metadata/_version.py
metadata/generated/data/policy/DataConsumerPolicy.py
metadata/generated/data/policy/DataStewardPolicy.py
metadata/generated/data/policy/__init__.py
metadata/generated/data/role/DataConsumer.py
metadata/generated/data/role/DataSteward.py
metadata/generated/data/role/__init__.py
metadata/generated/data/tags/__init__.py
metadata/generated/data/tags/personalDataTags.py
metadata/generated/data/tags/piiTags.py
metadata/generated/data/tags/tierTags.py
metadata/generated/schema/api/__init__.py
metadata/generated/schema/api/catalogVersion.py
metadata/generated/schema/api/setOwner.py
metadata/generated/schema/api/data/__init__.py
metadata/generated/schema/api/data/createChart.py
metadata/generated/schema/api/data/createDashboard.py
metadata/generated/schema/api/data/createDatabase.py
metadata/generated/schema/api/data/createDatabaseSchema.py
metadata/generated/schema/api/data/createGlossary.py
metadata/generated/schema/api/data/createGlossaryTerm.py
metadata/generated/schema/api/data/createLocation.py
metadata/generated/schema/api/data/createMlModel.py
metadata/generated/schema/api/data/createPipeline.py
metadata/generated/schema/api/data/createTable.py
metadata/generated/schema/api/data/createTopic.py
metadata/generated/schema/api/events/__init__.py
metadata/generated/schema/api/events/createWebhook.py
metadata/generated/schema/api/feed/__init__.py
metadata/generated/schema/api/feed/createPost.py
metadata/generated/schema/api/feed/createThread.py
metadata/generated/schema/api/feed/threadCount.py
metadata/generated/schema/api/lineage/__init__.py
metadata/generated/schema/api/lineage/addLineage.py
metadata/generated/schema/api/policies/__init__.py
metadata/generated/schema/api/policies/createPolicy.py
metadata/generated/schema/api/services/__init__.py
metadata/generated/schema/api/services/createDashboardService.py
metadata/generated/schema/api/services/createDatabaseService.py
metadata/generated/schema/api/services/createMessagingService.py
openmetadata_ingestion_core-0.10.0.dist-info/METADATA
openmetadata_ingestion_core-0.10.0.dist-info/WHEEL
openmetadata_ingestion_core-0.10.0.dist-info/top_level.txt
openmetadata_ingestion_core-0.10.0.dist-info/RECORD
