Metadata-Version: 2.1
Name: openmetadata-ingestion-core
Version: 0.10.0
Summary: These are the generated Python classes from JSON Schema
Home-page: https://open-metadata.org/
Author: OpenMetadata Committers
License: Apache License 2.0
Project-URL: Documentation, https://docs.open-metadata.org/
Project-URL: Source, https://github.com/open-metadata/OpenMetadata
Platform: UNKNOWN
Requires-Python: >=3.8
Requires-Dist: incremental
Provides-Extra: dev
Requires-Dist: datamodel-code-generator (==0.11.14) ; extra == 'dev'
Requires-Dist: twisted ; extra == 'dev'
Requires-Dist: incremental ; extra == 'dev'
Requires-Dist: click ; extra == 'dev'
Requires-Dist: black (==21.12b0) ; extra == 'dev'
Requires-Dist: twine ; extra == 'dev'
Requires-Dist: wheel ; extra == 'dev'
